[
 {
  "name": "삼육오상사",
  "address": "서울 동대문구 홍릉로 67 1층우측(청량리동)",
  "combination": "자동",
  "lat": 37.58633,
  "lng": 127.04299
 },
 {
  "name": "우일",
  "address": "서울 송파구 마천로 235",
  "combination": "수동",
  "lat": 37.49996,
  "lng": 127.14397
 },
 {
  "name": "한국인세계대박복권",
  "address": "인천 연수구 한나루로197번길 34",
  "combination": "자동",
  "lat": 37.42769,
  "lng": 126.65522
 },
 {
  "name": "해피+24시편의점",
  "address": "광주 북구 하서로 330",
  "combination": "자동",
  "lat": 35.2045,
  "lng": 126.8739
 },
 {
  "name": "삼산현대 로또판매",
  "address": "울산 남구 월평로 225",
  "combination": "자동",
  "lat": 35.54691,
  "lng": 129.3294
 },
 {
  "name": "후레쉬슈퍼",
  "address": "경기 부천시 부천로 80 풍산메디칼프라자 101호",
  "combination": "수동",
  "lat": 37.491283,
  "lng": 126.7847
 },
 {
  "name": "이마트24녹동점1등복권방",
  "address": "전남 고흥군 녹동남촌1길 13 이마트24녹동점옆",
  "combination": "자동",
  "lat": 34.525757,
  "lng": 127.14047
 },
 {
  "name": "로또 휴게",
  "address": "제주 제주시 연삼로 626",
  "combination": "자동",
  "lat": 33.5063,
  "lng": 126.55473
 }
]